nbviewer/__init__.py
nbviewer/main.py
nbviewer_gui-2.0.0.dist-info/LICENSE
nbviewer_gui-2.0.0.dist-info/METADATA
nbviewer_gui-2.0.0.dist-info/WHEEL
nbviewer_gui-2.0.0.dist-info/entry_points.txt
nbviewer_gui-2.0.0.dist-info/top_level.txt
nbviewer_gui-2.0.0.dist-info/RECORD
