Metadata-Version: 2.1
Name: nbviewer-gui
Version: 2.0.0
Summary: A Utility for previewing *.ipynb files in linux machines
Author: Jithin Johnson
License: MIT License
Project-URL: Bug Tracker, https://github.com/jithu7432/nb-viewer/issues
Project-URL: Homepage, https://github.com/jithu7432/nb-viewer
Classifier: License :: OSI Approved :: MIT License
Classifier: Operating System :: POSIX :: Linux
Classifier: Programming Language :: Python :: 3
Classifier: Programming Language :: Python :: 3 :: Only
Classifier: Programming Language :: Python :: 3.7
Classifier: Programming Language :: Python :: 3.8
Classifier: Programming Language :: Python :: 3.9
Classifier: Programming Language :: Python :: 3.10
Requires-Python: >=3.7
License-File: LICENSE
Requires-Dist: ipython ==8.4.0
Requires-Dist: nbconvert ==6.5.0
Requires-Dist: nbformat ==5.4.0
Requires-Dist: PyQtWebEngine ==5.15.5
